Compiled from "Cp14_SimpleString.java"
public class Cp14_SimpleString {
  public Cp14_SimpleString();
    Code:
       0: aload_0
       1: invokespecial #1                  // Method java/lang/Object."<init>":()V
       4: return

  public static void main(java.lang.String[]);
    Code:
       0: ldc           #7                  // String A Simple Test String.
       2: astore_1
       3: ldc           #9                  // String A Simple Concatenated String.
       5: astore_2
       6: getstatic     #11                 // Field java/lang/System.out:Ljava/io/PrintStream;
       9: aload_1
      10: invokevirtual #17                 // Method java/io/PrintStream.println:(Ljava/lang/String;)V
      13: getstatic     #11                 // Field java/lang/System.out:Ljava/io/PrintStream;
      16: aload_2
      17: invokevirtual #17                 // Method java/io/PrintStream.println:(Ljava/lang/String;)V
      20: return
}
